istrings.py
setup.py
istrings.egg-info/PKG-INFO
istrings.egg-info/SOURCES.txt
istrings.egg-info/dependency_links.txt
istrings.egg-info/top_level.txt