Metadata-Version: 1.1
Name: istrings
Version: 0.0.2
Summary: Simple module to work with interface texts outside of the main code
Home-page: http://github.com/bobuk/istrings
Author: Grigory Bakunov
Author-email: thebobuk@ya.ru
License: UNKNOWN
Platform: UNKNOWN
Classifier: Programming Language :: Python
Classifier: Programming Language :: Python :: 3
Classifier: Development Status :: 4 - Beta
Classifier: Environment :: Other Environment
Classifier: Intended Audience :: Developers
Classifier: Operating System :: OS Independent
Classifier: Topic :: Software Development :: Libraries :: Python Modules
